{"cutToTop":3,"date":"2023-12-16","eliminationPlayers":[{"id":1671,"name":"Alpi","rank":1,"seed":1},{"id":1670,"name":"Ayyliens","rank":2,"seed":2},{"id":1669,"name":"RubenPieters","rank":3,"seed":3}],"links":[{"href":"http://steffens.org/nrtm/nrtm-schema.json","rel":"schemaderivedfrom"},{"href":"https://github.com/Chemscribbler/sass","rel":"uploadedfrom"}],"name":"Gent CO2","players":[{"corpIdentity":"MirrorMorph: Endless Iteration","extendedStrengthOfSchedule":1.708,"id":1671,"matchPoints":15,"name":"Alpi","rank":1,"runnerIdentity":"Lat: Ethical Freelancer","sideBalance":0,"strengthOfSchedule":1.5},{"corpIdentity":"Ob Superheavy Logistics: Extract. Export. Excel.","extendedStrengthOfSchedule":1.472,"id":1670,"matchPoints":12,"name":"Ayyliens","rank":2,"runnerIdentity":"Lat: Ethical Freelancer","sideBalance":0,"strengthOfSchedule":1.667},{"corpIdentity":"AgInfusion: New Miracles for a New World","extendedStrengthOfSchedule":1.403,"id":1669,"matchPoints":9,"name":"RubenPieters","rank":3,"runnerIdentity":"Ren\u00e9 \"Loup\" Arcemont: Party Animal","sideBalance":0,"strengthOfSchedule":1.833},{"corpIdentity":"AgInfusion: New Miracles for a New World","extendedStrengthOfSchedule":1.5,"id":1664,"matchPoints":9,"name":"FREDPI","rank":4,"runnerIdentity":"Lat: Ethical Freelancer","sideBalance":0,"strengthOfSchedule":1.667},{"corpIdentity":"Near-Earth Hub: Broadcast Center","extendedStrengthOfSchedule":1.528,"id":1668,"matchPoints":9,"name":"roeiboot4","rank":5,"runnerIdentity":"Nyusha \"Sable\" Sintashta: Symphonic Prodigy","sideBalance":0,"strengthOfSchedule":1.417},{"corpIdentity":"Near-Earth Hub: Broadcast Center","extendedStrengthOfSchedule":1.611,"id":1665,"matchPoints":9,"name":"Okkdoko","rank":6,"runnerIdentity":"Ren\u00e9 \"Loup\" Arcemont: Party Animal","sideBalance":0,"strengthOfSchedule":1.167},{"corpIdentity":"Asa Group: Security Through Vigilance","extendedStrengthOfSchedule":1.472,"id":1667,"matchPoints":6,"name":"Bramboo","rank":7,"runnerIdentity":"Az McCaffrey: Mechanical Prodigy","sideBalance":0,"strengthOfSchedule":1.167},{"corpIdentity":"Azmari EdTech: Shaping the Future","extendedStrengthOfSchedule":1.306,"id":1666,"matchPoints":3,"name":"Cluster Fox","rank":8,"runnerIdentity":"Rielle \"Kit\" Peddler: Transhuman","sideBalance":0,"strengthOfSchedule":1.583}],"preliminaryRounds":6,"rounds":[[{"corpIdentity":"Near-Earth Hub: Broadcast Center","corpPlayer":1665,"corpScore":"3","runnerIdentity":"Az McCaffrey: Mechanical Prodigy","runnerPlayer":1667,"runnerScore":"0","tableNumber":2},{"corpIdentity":"Near-Earth Hub: Broadcast Center","corpPlayer":1668,"corpScore":"0","runnerIdentity":"Ren\u00e9 \"Loup\" Arcemont: Party Animal","runnerPlayer":1669,"runnerScore":"3","tableNumber":4},{"corpIdentity":"Azmari EdTech: Shaping the Future","corpPlayer":1666,"corpScore":"0","runnerIdentity":"Lat: Ethical Freelancer","runnerPlayer":1670,"runnerScore":"3","tableNumber":1},{"corpIdentity":"AgInfusion: New Miracles for a New World","corpPlayer":1664,"corpScore":"0","runnerIdentity":"Lat: Ethical Freelancer","runnerPlayer":1671,"runnerScore":"3","tableNumber":3}],[{"corpIdentity":"MirrorMorph: Endless Iteration","corpPlayer":1671,"corpScore":"3","runnerIdentity":"Rielle \"Kit\" Peddler: Transhuman","runnerPlayer":1666,"runnerScore":"0","tableNumber":3},{"corpIdentity":"Ob Superheavy Logistics: Extract. Export. Excel.","corpPlayer":1670,"corpScore":"3","runnerIdentity":"Ren\u00e9 \"Loup\" Arcemont: Party Animal","runnerPlayer":1665,"runnerScore":"0","tableNumber":1},{"corpIdentity":"AgInfusion: New Miracles for a New World","corpPlayer":1669,"corpScore":"0","runnerIdentity":"Lat: Ethical Freelancer","runnerPlayer":1664,"runnerScore":"3","tableNumber":2},{"corpIdentity":"Asa Group: Security Through Vigilance","corpPlayer":1667,"corpScore":"0","runnerIdentity":"Nyusha \"Sable\" Sintashta: Symphonic Prodigy","runnerPlayer":1668,"runnerScore":"3","tableNumber":4}],[{"corpIdentity":"Ob Superheavy Logistics: Extract. Export. Excel.","corpPlayer":1670,"corpScore":"3","runnerIdentity":"Lat: Ethical Freelancer","runnerPlayer":1671,"runnerScore":"0","tableNumber":1},{"corpIdentity":"Asa Group: Security Through Vigilance","corpPlayer":1667,"corpScore":"3","runnerIdentity":"Rielle \"Kit\" Peddler: Transhuman","runnerPlayer":1666,"runnerScore":"0","tableNumber":4},{"corpIdentity":"AgInfusion: New Miracles for a New World","corpPlayer":1664,"corpScore":"3","runnerIdentity":"Nyusha \"Sable\" Sintashta: Symphonic Prodigy","runnerPlayer":1668,"runnerScore":"0","tableNumber":2},{"corpIdentity":"AgInfusion: New Miracles for a New World","corpPlayer":1669,"corpScore":"3","runnerIdentity":"Ren\u00e9 \"Loup\" Arcemont: Party Animal","runnerPlayer":1665,"runnerScore":"0","tableNumber":3}],[{"corpIdentity":"Near-Earth Hub: Broadcast Center","corpPlayer":1665,"corpScore":"0","runnerIdentity":"Ren\u00e9 \"Loup\" Arcemont: Party Animal","runnerPlayer":1669,"runnerScore":"3","tableNumber":2},{"corpIdentity":"MirrorMorph: Endless Iteration","corpPlayer":1671,"corpScore":"3","runnerIdentity":"Lat: Ethical Freelancer","runnerPlayer":1670,"runnerScore":"0","tableNumber":1},{"corpIdentity":"Near-Earth Hub: Broadcast Center","corpPlayer":1668,"corpScore":"0","runnerIdentity":"Lat: Ethical Freelancer","runnerPlayer":1664,"runnerScore":"3","tableNumber":3},{"corpIdentity":"Azmari EdTech: Shaping the Future","corpPlayer":1666,"corpScore":"3","runnerIdentity":"Az McCaffrey: Mechanical Prodigy","runnerPlayer":1667,"runnerScore":"0","tableNumber":4}],[{"corpIdentity":"AgInfusion: New Miracles for a New World","corpPlayer":1664,"corpScore":"0","runnerIdentity":"Lat: Ethical Freelancer","runnerPlayer":1670,"runnerScore":"3","tableNumber":2},{"corpIdentity":"MirrorMorph: Endless Iteration","corpPlayer":1671,"corpScore":"3","runnerIdentity":"Ren\u00e9 \"Loup\" Arcemont: Party Animal","runnerPlayer":1669,"runnerScore":"0","tableNumber":1},{"corpIdentity":"Azmari EdTech: Shaping the Future","corpPlayer":1666,"corpScore":"0","runnerIdentity":"Ren\u00e9 \"Loup\" Arcemont: Party Animal","runnerPlayer":1665,"runnerScore":"3","tableNumber":4},{"corpIdentity":"Near-Earth Hub: Broadcast Center","corpPlayer":1668,"corpScore":"3","runnerIdentity":"Az McCaffrey: Mechanical Prodigy","runnerPlayer":1667,"runnerScore":"0","tableNumber":3}],[{"corpIdentity":"AgInfusion: New Miracles for a New World","corpPlayer":1669,"corpScore":"0","runnerIdentity":"Lat: Ethical Freelancer","runnerPlayer":1671,"runnerScore":"3","tableNumber":1},{"corpIdentity":"Near-Earth Hub: Broadcast Center","corpPlayer":1665,"corpScore":"3","runnerIdentity":"Rielle \"Kit\" Peddler: Transhuman","runnerPlayer":1666,"runnerScore":"0","tableNumber":4},{"corpIdentity":"Ob Superheavy Logistics: Extract. Export. Excel.","corpPlayer":1670,"corpScore":"0","runnerIdentity":"Nyusha \"Sable\" Sintashta: Symphonic Prodigy","runnerPlayer":1668,"runnerScore":"3","tableNumber":2},{"corpIdentity":"Asa Group: Security Through Vigilance","corpPlayer":1667,"corpScore":"3","runnerIdentity":"Lat: Ethical Freelancer","runnerPlayer":1664,"runnerScore":"0","tableNumber":3}],[{"corpPlayer":1670,"eliminationGame":true,"loser_id":1669,"runnerPlayer":1669,"tableNumber":1,"winner_id":1670}],[{"corpPlayer":1670,"eliminationGame":true,"loser_id":1670,"runnerPlayer":1671,"tableNumber":2,"winner_id":1671}]],"uploadedFrom":"AesopsTables"}