{"cutToTop":4,"date":"2024-03-30","eliminationPlayers":[{"id":2671,"name":"OF15-15","rank":1,"seed":3},{"id":2669,"name":"AlPi","rank":2,"seed":2},{"id":2706,"name":"CobraBubbles","rank":3,"seed":1},{"id":2705,"name":"Jai","rank":4,"seed":4}],"links":[{"href":"http://steffens.org/nrtm/nrtm-schema.json","rel":"schemaderivedfrom"},{"href":"https://github.com/Chemscribbler/sass","rel":"uploadedfrom"}],"name":"Fly to EMEA #1","players":[{"corpIdentity":"Ob Superheavy Logistics: Extract. Export. Excel.","extendedStrengthOfSchedule":1.609,"id":2706,"matchPoints":15,"name":"CobraBubbles","rank":1,"runnerIdentity":"Hoshiko Shiro: Untold Protagonist","sideBalance":0,"strengthOfSchedule":1.667},{"corpIdentity":"MirrorMorph: Endless Iteration","extendedStrengthOfSchedule":1.609,"id":2669,"matchPoints":15,"name":"AlPi","rank":2,"runnerIdentity":"Lat: Ethical Freelancer","sideBalance":0,"strengthOfSchedule":1.583},{"corpIdentity":"Near-Earth Hub: Broadcast Center","extendedStrengthOfSchedule":1.718,"id":2671,"matchPoints":15,"name":"OF15-15","rank":3,"runnerIdentity":"Hoshiko Shiro: Untold Protagonist","sideBalance":0,"strengthOfSchedule":1.458},{"corpIdentity":"MirrorMorph: Endless Iteration","extendedStrengthOfSchedule":1.609,"id":2710,"matchPoints":15,"name":"testrunning","rank":4,"runnerIdentity":"Arissana Rocha Nahu: Street Artist","sideBalance":0,"strengthOfSchedule":1.403},{"corpIdentity":"AgInfusion: New Miracles for a New World","extendedStrengthOfSchedule":1.519,"id":2705,"matchPoints":12,"name":"Jai","rank":5,"runnerIdentity":"Arissana Rocha Nahu: Street Artist","sideBalance":0,"strengthOfSchedule":1.708},{"corpIdentity":"Asa Group: Security Through Vigilance","extendedStrengthOfSchedule":1.5,"id":2698,"matchPoints":12,"name":"krysdreavus","rank":6,"runnerIdentity":"Hoshiko Shiro: Untold Protagonist","sideBalance":0,"strengthOfSchedule":1.611},{"corpIdentity":"Haas-Bioroid: Precision Design","extendedStrengthOfSchedule":1.56,"id":2704,"matchPoints":12,"name":"NinQT","rank":7,"runnerIdentity":"Ken \u201cExpress\u201d Tenma: Disappeared Clone","sideBalance":0,"strengthOfSchedule":1.458},{"corpIdentity":"Epiphany Analytica: Nations Undivided","extendedStrengthOfSchedule":1.384,"id":2670,"matchPoints":10,"name":"Mortivor","rank":8,"runnerIdentity":"Arissana Rocha Nahu: Street Artist","sideBalance":0,"strengthOfSchedule":1.444},{"corpIdentity":"Azmari EdTech: Shaping the Future","extendedStrengthOfSchedule":1.468,"id":2711,"matchPoints":9,"name":"Atien","rank":9,"runnerIdentity":"Lat: Ethical Freelancer","sideBalance":0,"strengthOfSchedule":1.792},{"corpIdentity":"Azmari EdTech: Shaping the Future","extendedStrengthOfSchedule":1.38,"id":2712,"matchPoints":9,"name":"Silent Arbiter","rank":10,"runnerIdentity":"Arissana Rocha Nahu: Street Artist","sideBalance":0,"strengthOfSchedule":1.667},{"corpIdentity":"Haas-Bioroid: Precision Design","extendedStrengthOfSchedule":1.507,"id":2701,"matchPoints":9,"name":"Tradon","rank":11,"runnerIdentity":"Nyusha \"Sable\" Sintashta: Symphonic Prodigy","sideBalance":0,"strengthOfSchedule":1.611},{"corpIdentity":"AgInfusion: New Miracles for a New World","extendedStrengthOfSchedule":1.426,"id":2700,"matchPoints":9,"name":"xiaat","rank":12,"runnerIdentity":"Hoshiko Shiro: Untold Protagonist","sideBalance":0,"strengthOfSchedule":1.417},{"corpIdentity":"Jinteki: Personal Evolution","extendedStrengthOfSchedule":1.384,"id":2713,"matchPoints":9,"name":"Porkobolo","rank":13,"runnerIdentity":"Rielle \u201cKit\u201d Peddler: Transhuman","sideBalance":1,"strengthOfSchedule":1.333},{"corpIdentity":"Azmari EdTech: Shaping the Future","extendedStrengthOfSchedule":1.35,"id":2697,"matchPoints":9,"name":"Harper (l0velace)","rank":14,"runnerIdentity":"Arissana Rocha Nahu: Street Artist","sideBalance":1,"strengthOfSchedule":1.153},{"corpIdentity":"Haas-Bioroid: Precision Design","extendedStrengthOfSchedule":1.382,"id":2714,"matchPoints":9,"name":"Dragons1rule","rank":15,"runnerIdentity":"Hoshiko Shiro: Untold Protagonist","sideBalance":1,"strengthOfSchedule":1.139},{"corpIdentity":"NBN: Reality Plus","extendedStrengthOfSchedule":1.282,"id":2702,"matchPoints":9,"name":"davz131","rank":16,"runnerIdentity":"Rielle \u201cKit\u201d Peddler: Transhuman","sideBalance":-1,"strengthOfSchedule":1.097},{"corpIdentity":"Haas-Bioroid: Precision Design","extendedStrengthOfSchedule":1.343,"id":2672,"matchPoints":7,"name":"AugustusCaesar","rank":17,"runnerIdentity":"Arissana Rocha Nahu: Street Artist","sideBalance":0,"strengthOfSchedule":1.611},{"corpIdentity":"Asa Group: Security Through Vigilance","extendedStrengthOfSchedule":1.394,"id":2668,"matchPoints":6,"name":"HaverOfFun","rank":18,"runnerIdentity":"Ren\u00e9 \u201cLoup\u201d Arcemont: Party Animal","sideBalance":0,"strengthOfSchedule":1.778},{"corpIdentity":"Thule Subsea: Safety Below","extendedStrengthOfSchedule":1.28,"id":2715,"matchPoints":6,"name":"asphyxia","rank":19,"runnerIdentity":"Arissana Rocha Nahu: Street Artist","sideBalance":-1,"strengthOfSchedule":1.667},{"corpIdentity":"A Teia: IP Recovery","extendedStrengthOfSchedule":1.552,"id":2699,"matchPoints":6,"name":"Stwyde","rank":20,"runnerIdentity":"Captain Padma Isbister: Intrepid Explorer","sideBalance":0,"strengthOfSchedule":1.625},{"corpIdentity":"Ob Superheavy Logistics: Extract. Export. Excel.","extendedStrengthOfSchedule":1.118,"id":2703,"matchPoints":6,"name":"Bemi","rank":21,"runnerIdentity":"Hoshiko Shiro: Untold Protagonist","sideBalance":-1,"strengthOfSchedule":1.278},{"corpIdentity":"Weyland Consortium: Building a Better World","extendedStrengthOfSchedule":1.572,"id":2695,"matchPoints":6,"name":"Scarius","rank":22,"runnerIdentity":"Es\u00e2 Afontov: Eco-Insurrectionist","sideBalance":0,"strengthOfSchedule":1.042},{"corpIdentity":"NBN: Reality Plus","extendedStrengthOfSchedule":1.417,"id":2708,"matchPoints":3,"name":"Fridan","rank":23,"runnerIdentity":"Hoshiko Shiro: Untold Protagonist","sideBalance":0,"strengthOfSchedule":1.875},{"corpIdentity":"Ob Superheavy Logistics: Extract. Export. Excel.","extendedStrengthOfSchedule":1.361,"id":2707,"matchPoints":3,"name":"not_yeti","rank":24,"runnerIdentity":"Hoshiko Shiro: Untold Protagonist","sideBalance":0,"strengthOfSchedule":1.75},{"corpIdentity":"NBN: Reality Plus","extendedStrengthOfSchedule":1.417,"id":2709,"matchPoints":0,"name":"sohum","rank":25,"runnerIdentity":"Zahya Sadeghi: Versatile Smuggler","sideBalance":0,"strengthOfSchedule":1.625}],"preliminaryRounds":6,"rounds":[[{"corpIdentity":"Ob Superheavy Logistics: Extract. Export. Excel.","corpPlayer":2703,"corpScore":"0","runnerIdentity":"Ken \u201cExpress\u201d Tenma: Disappeared Clone","runnerPlayer":2704,"runnerScore":"3","tableNumber":10},{"corpIdentity":"MirrorMorph: Endless Iteration","corpPlayer":2710,"corpScore":"3","runnerIdentity":"Arissana Rocha Nahu: Street Artist","runnerPlayer":2712,"runnerScore":"0","tableNumber":5},{"corpIdentity":"Ob Superheavy Logistics: Extract. Export. Excel.","corpPlayer":2707,"corpScore":"0","runnerIdentity":"Lat: Ethical Freelancer","runnerPlayer":2711,"runnerScore":"3","tableNumber":11},{"corpIdentity":"Weyland Consortium: Building a Better World","corpPlayer":2695,"corpScore":"0","runnerIdentity":"Ren\u00e9 \u201cLoup\u201d Arcemont: Party Animal","runnerPlayer":2668,"runnerScore":"3","tableNumber":12},{"corpIdentity":"Azmari EdTech: Shaping the Future","corpPlayer":2697,"corpScore":"0","runnerIdentity":"Arissana Rocha Nahu: Street Artist","runnerPlayer":2672,"runnerScore":"3","tableNumber":7},{"corpIdentity":"Jinteki: Personal Evolution","corpPlayer":2713,"corpScore":"3","runnerIdentity":"","runnerPlayer":"(BYE)","runnerScore":"0","tableNumber":13},{"corpIdentity":"Asa Group: Security Through Vigilance","corpPlayer":2698,"corpScore":"3","runnerIdentity":"Rielle \u201cKit\u201d Peddler: Transhuman","runnerPlayer":2702,"runnerScore":"0","tableNumber":6},{"corpIdentity":"NBN: Reality Plus","corpPlayer":2708,"corpScore":"3","runnerIdentity":"Hoshiko Shiro: Untold Protagonist","runnerPlayer":2671,"runnerScore":"0","tableNumber":4},{"corpIdentity":"A Teia: IP Recovery","corpPlayer":2699,"corpScore":"3","runnerIdentity":"Zahya Sadeghi: Versatile Smuggler","runnerPlayer":2709,"runnerScore":"0","tableNumber":3},{"corpIdentity":"MirrorMorph: Endless Iteration","corpPlayer":2669,"corpScore":"3","runnerIdentity":"Arissana Rocha Nahu: Street Artist","runnerPlayer":2715,"runnerScore":"0","tableNumber":8},{"corpIdentity":"Haas-Bioroid: Precision Design","corpPlayer":2714,"corpScore":"3","runnerIdentity":"Arissana Rocha Nahu: Street Artist","runnerPlayer":2670,"runnerScore":"0","tableNumber":1},{"corpIdentity":"Ob Superheavy Logistics: Extract. Export. Excel.","corpPlayer":2706,"corpScore":"3","runnerIdentity":"Hoshiko Shiro: Untold Protagonist","runnerPlayer":2700,"runnerScore":"0","tableNumber":2},{"corpIdentity":"Haas-Bioroid: Precision Design","corpPlayer":2701,"corpScore":"3","runnerIdentity":"Arissana Rocha Nahu: Street Artist","runnerPlayer":2705,"runnerScore":"0","tableNumber":9}],[{"corpIdentity":"Thule Subsea: Safety Below","corpPlayer":2715,"corpScore":"3","runnerIdentity":"","runnerPlayer":"(BYE)","runnerScore":"0","tableNumber":13},{"corpIdentity":"Haas-Bioroid: Precision Design","corpPlayer":2672,"corpScore":"0","runnerIdentity":"Hoshiko Shiro: Untold Protagonist","runnerPlayer":2698,"runnerScore":"3","tableNumber":4},{"corpIdentity":"AgInfusion: New Miracles for a New World","corpPlayer":2700,"corpScore":"3","runnerIdentity":"Es\u00e2 Afontov: Eco-Insurrectionist","runnerPlayer":2695,"runnerScore":"0","tableNumber":12},{"corpIdentity":"Haas-Bioroid: Precision Design","corpPlayer":2704,"corpScore":"3","runnerIdentity":"Hoshiko Shiro: Untold Protagonist","runnerPlayer":2708,"runnerScore":"0","tableNumber":3},{"corpIdentity":"Azmari EdTech: Shaping the Future","corpPlayer":2712,"corpScore":"3","runnerIdentity":"Hoshiko Shiro: Untold Protagonist","runnerPlayer":2703,"runnerScore":"0","tableNumber":10},{"corpIdentity":"Azmari EdTech: Shaping the Future","corpPlayer":2711,"corpScore":"3","runnerIdentity":"Hoshiko Shiro: Untold Protagonist","runnerPlayer":2714,"runnerScore":"0","tableNumber":2},{"corpIdentity":"Jinteki: Personal Evolution","corpPlayer":2713,"corpScore":"0","runnerIdentity":"Captain Padma Isbister: Intrepid Explorer","runnerPlayer":2699,"runnerScore":"3","tableNumber":1},{"corpIdentity":"AgInfusion: New Miracles for a New World","corpPlayer":2705,"corpScore":"3","runnerIdentity":"Arissana Rocha Nahu: Street Artist","runnerPlayer":2697,"runnerScore":"0","tableNumber":9},{"corpIdentity":"Asa Group: Security Through Vigilance","corpPlayer":2668,"corpScore":"0","runnerIdentity":"Hoshiko Shiro: Untold Protagonist","runnerPlayer":2706,"runnerScore":"3","tableNumber":5},{"corpIdentity":"Near-Earth Hub: Broadcast Center","corpPlayer":2671,"corpScore":"3","runnerIdentity":"Nyusha \"Sable\" Sintashta: Symphonic Prodigy","runnerPlayer":2701,"runnerScore":"0","tableNumber":7},{"corpIdentity":"NBN: Reality Plus","corpPlayer":2702,"corpScore":"0","runnerIdentity":"Hoshiko Shiro: Untold Protagonist","runnerPlayer":2707,"runnerScore":"3","tableNumber":11},{"corpIdentity":"NBN: Reality Plus","corpPlayer":2709,"corpScore":"0","runnerIdentity":"Lat: Ethical Freelancer","runnerPlayer":2669,"runnerScore":"3","tableNumber":8},{"corpIdentity":"Epiphany Analytica: Nations Undivided","corpPlayer":2670,"corpScore":"3","runnerIdentity":"Arissana Rocha Nahu: Street Artist","runnerPlayer":2710,"runnerScore":"0","tableNumber":6}],[{"corpIdentity":"Azmari EdTech: Shaping the Future","corpPlayer":2697,"corpScore":"3","runnerIdentity":"","runnerPlayer":"(BYE)","runnerScore":"0","tableNumber":13},{"corpIdentity":"Ob Superheavy Logistics: Extract. Export. Excel.","corpPlayer":2703,"corpScore":"0","runnerIdentity":"Rielle \u201cKit\u201d Peddler: Transhuman","runnerPlayer":2702,"runnerScore":"3","tableNumber":12},{"corpIdentity":"Azmari EdTech: Shaping the Future","corpPlayer":2712,"corpScore":"3","runnerIdentity":"Hoshiko Shiro: Untold Protagonist","runnerPlayer":2714,"runnerScore":"0","tableNumber":7},{"corpIdentity":"Asa Group: Security Through Vigilance","corpPlayer":2668,"corpScore":"0","runnerIdentity":"Hoshiko Shiro: Untold Protagonist","runnerPlayer":2671,"runnerScore":"3","tableNumber":6},{"corpIdentity":"Haas-Bioroid: Precision Design","corpPlayer":2704,"corpScore":"3","runnerIdentity":"Lat: Ethical Freelancer","runnerPlayer":2711,"runnerScore":"0","tableNumber":2},{"corpIdentity":"NBN: Reality Plus","corpPlayer":2709,"corpScore":"0","runnerIdentity":"Es\u00e2 Afontov: Eco-Insurrectionist","runnerPlayer":2695,"runnerScore":"3","tableNumber":11},{"corpIdentity":"MirrorMorph: Endless Iteration","corpPlayer":2710,"corpScore":"3","runnerIdentity":"Hoshiko Shiro: Untold Protagonist","runnerPlayer":2707,"runnerScore":"0","tableNumber":9},{"corpIdentity":"Asa Group: Security Through Vigilance","corpPlayer":2698,"corpScore":"0","runnerIdentity":"Lat: Ethical Freelancer","runnerPlayer":2669,"runnerScore":"3","tableNumber":3},{"corpIdentity":"NBN: Reality Plus","corpPlayer":2708,"corpScore":"0","runnerIdentity":"Arissana Rocha Nahu: Street Artist","runnerPlayer":2705,"runnerScore":"3","tableNumber":5},{"corpIdentity":"A Teia: IP Recovery","corpPlayer":2699,"corpScore":"0","runnerIdentity":"Hoshiko Shiro: Untold Protagonist","runnerPlayer":2706,"runnerScore":"3","tableNumber":1},{"corpIdentity":"Haas-Bioroid: Precision Design","corpPlayer":2701,"corpScore":"0","runnerIdentity":"Rielle \u201cKit\u201d Peddler: Transhuman","runnerPlayer":2713,"runnerScore":"3","tableNumber":8},{"corpIdentity":"Thule Subsea: Safety Below","corpPlayer":2715,"corpScore":"3","runnerIdentity":"Hoshiko Shiro: Untold Protagonist","runnerPlayer":2700,"runnerScore":"0","tableNumber":10},{"corpIdentity":"Epiphany Analytica: Nations Undivided","corpPlayer":2670,"corpScore":"1","runnerIdentity":"Arissana Rocha Nahu: Street Artist","runnerPlayer":2672,"runnerScore":"1","tableNumber":4}],[{"corpIdentity":"AgInfusion: New Miracles for a New World","corpPlayer":2705,"corpScore":"3","runnerIdentity":"Hoshiko Shiro: Untold Protagonist","runnerPlayer":2698,"runnerScore":"0","tableNumber":5},{"corpIdentity":"Ob Superheavy Logistics: Extract. Export. Excel.","corpPlayer":2703,"corpScore":"3","runnerIdentity":"","runnerPlayer":"(BYE)","runnerScore":"0","tableNumber":13},{"corpIdentity":"Near-Earth Hub: Broadcast Center","corpPlayer":2671,"corpScore":"3","runnerIdentity":"Arissana Rocha Nahu: Street Artist","runnerPlayer":2712,"runnerScore":"0","tableNumber":3},{"corpIdentity":"Weyland Consortium: Building a Better World","corpPlayer":2695,"corpScore":"3","runnerIdentity":"Hoshiko Shiro: Untold Protagonist","runnerPlayer":2708,"runnerScore":"0","tableNumber":11},{"corpIdentity":"Ob Superheavy Logistics: Extract. Export. Excel.","corpPlayer":2707,"corpScore":"0","runnerIdentity":"Arissana Rocha Nahu: Street Artist","runnerPlayer":2697,"runnerScore":"3","tableNumber":9},{"corpIdentity":"Azmari EdTech: Shaping the Future","corpPlayer":2711,"corpScore":"3","runnerIdentity":"Rielle \u201cKit\u201d Peddler: Transhuman","runnerPlayer":2713,"runnerScore":"0","tableNumber":6},{"corpIdentity":"MirrorMorph: Endless Iteration","corpPlayer":2669,"corpScore":"3","runnerIdentity":"Captain Padma Isbister: Intrepid Explorer","runnerPlayer":2699,"runnerScore":"0","tableNumber":2},{"corpIdentity":"Haas-Bioroid: Precision Design","corpPlayer":2714,"corpScore":"0","runnerIdentity":"Ren\u00e9 \u201cLoup\u201d Arcemont: Party Animal","runnerPlayer":2668,"runnerScore":"3","tableNumber":10},{"corpIdentity":"NBN: Reality Plus","corpPlayer":2702,"corpScore":"3","runnerIdentity":"Arissana Rocha Nahu: Street Artist","runnerPlayer":2670,"runnerScore":"0","tableNumber":7},{"corpIdentity":"AgInfusion: New Miracles for a New World","corpPlayer":2700,"corpScore":"3","runnerIdentity":"Zahya Sadeghi: Versatile Smuggler","runnerPlayer":2709,"runnerScore":"0","tableNumber":12},{"corpIdentity":"Ob Superheavy Logistics: Extract. Export. Excel.","corpPlayer":2706,"corpScore":"3","runnerIdentity":"Ken \u201cExpress\u201d Tenma: Disappeared Clone","runnerPlayer":2704,"runnerScore":"0","tableNumber":1},{"corpIdentity":"Haas-Bioroid: Precision Design","corpPlayer":2672,"corpScore":"0","runnerIdentity":"Nyusha \"Sable\" Sintashta: Symphonic Prodigy","runnerPlayer":2701,"runnerScore":"3","tableNumber":8},{"corpIdentity":"Thule Subsea: Safety Below","corpPlayer":2715,"corpScore":"0","runnerIdentity":"Arissana Rocha Nahu: Street Artist","runnerPlayer":2710,"runnerScore":"3","tableNumber":4}],[{"corpIdentity":"Jinteki: Personal Evolution","corpPlayer":2713,"corpScore":"3","runnerIdentity":"Arissana Rocha Nahu: Street Artist","runnerPlayer":2712,"runnerScore":"0","tableNumber":6},{"corpIdentity":"Near-Earth Hub: Broadcast Center","corpPlayer":2671,"corpScore":"3","runnerIdentity":"Lat: Ethical Freelancer","runnerPlayer":2711,"runnerScore":"0","tableNumber":2},{"corpIdentity":"Haas-Bioroid: Precision Design","corpPlayer":2714,"corpScore":"3","runnerIdentity":"","runnerPlayer":"(BYE)","runnerScore":"0","tableNumber":11},{"corpIdentity":"Haas-Bioroid: Precision Design","corpPlayer":2672,"corpScore":"3","runnerIdentity":"Rielle \u201cKit\u201d Peddler: Transhuman","runnerPlayer":2702,"runnerScore":"0","tableNumber":9},{"corpIdentity":"Haas-Bioroid: Precision Design","corpPlayer":2704,"corpScore":"3","runnerIdentity":"Es\u00e2 Afontov: Eco-Insurrectionist","runnerPlayer":2695,"runnerScore":"0","tableNumber":4},{"corpIdentity":"Ob Superheavy Logistics: Extract. Export. Excel.","corpPlayer":2706,"corpScore":"0","runnerIdentity":"Lat: Ethical Freelancer","runnerPlayer":2669,"runnerScore":"3","tableNumber":1},{"corpIdentity":"Haas-Bioroid: Precision Design","corpPlayer":2701,"corpScore":"3","runnerIdentity":"Ren\u00e9 \u201cLoup\u201d Arcemont: Party Animal","runnerPlayer":2668,"runnerScore":"0","tableNumber":5},{"corpIdentity":"Azmari EdTech: Shaping the Future","corpPlayer":2697,"corpScore":"0","runnerIdentity":"Hoshiko Shiro: Untold Protagonist","runnerPlayer":2700,"runnerScore":"3","tableNumber":8},{"corpIdentity":"MirrorMorph: Endless Iteration","corpPlayer":2710,"corpScore":"3","runnerIdentity":"Arissana Rocha Nahu: Street Artist","runnerPlayer":2705,"runnerScore":"0","tableNumber":3},{"corpIdentity":"Asa Group: Security Through Vigilance","corpPlayer":2698,"corpScore":"3","runnerIdentity":"Arissana Rocha Nahu: Street Artist","runnerPlayer":2715,"runnerScore":"0","tableNumber":7},{"corpIdentity":"Epiphany Analytica: Nations Undivided","corpPlayer":2670,"corpScore":"3","runnerIdentity":"Hoshiko Shiro: Untold Protagonist","runnerPlayer":2703,"runnerScore":"0","tableNumber":10}],[{"corpIdentity":"NBN: Reality Plus","corpPlayer":2702,"corpScore":"3","runnerIdentity":"","runnerPlayer":"(BYE)","runnerScore":"0","tableNumber":11},{"corpIdentity":"Azmari EdTech: Shaping the Future","corpPlayer":2712,"corpScore":"3","runnerIdentity":"Arissana Rocha Nahu: Street Artist","runnerPlayer":2715,"runnerScore":"0","tableNumber":9},{"corpIdentity":"Haas-Bioroid: Precision Design","corpPlayer":2714,"corpScore":"3","runnerIdentity":"Arissana Rocha Nahu: Street Artist","runnerPlayer":2672,"runnerScore":"0","tableNumber":8},{"corpIdentity":"Weyland Consortium: Building a Better World","corpPlayer":2695,"corpScore":"0","runnerIdentity":"Hoshiko Shiro: Untold Protagonist","runnerPlayer":2703,"runnerScore":"3","tableNumber":10},{"corpIdentity":"Jinteki: Personal Evolution","corpPlayer":2713,"corpScore":"0","runnerIdentity":"Hoshiko Shiro: Untold Protagonist","runnerPlayer":2698,"runnerScore":"3","tableNumber":5},{"corpIdentity":"AgInfusion: New Miracles for a New World","corpPlayer":2705,"corpScore":"3","runnerIdentity":"Ken \u201cExpress\u201d Tenma: Disappeared Clone","runnerPlayer":2704,"runnerScore":"0","tableNumber":3},{"corpIdentity":"MirrorMorph: Endless Iteration","corpPlayer":2669,"corpScore":"0","runnerIdentity":"Hoshiko Shiro: Untold Protagonist","runnerPlayer":2671,"runnerScore":"3","tableNumber":1},{"corpIdentity":"Azmari EdTech: Shaping the Future","corpPlayer":2697,"corpScore":"3","runnerIdentity":"Nyusha \"Sable\" Sintashta: Symphonic Prodigy","runnerPlayer":2701,"runnerScore":"0","tableNumber":6},{"corpIdentity":"AgInfusion: New Miracles for a New World","corpPlayer":2700,"corpScore":"0","runnerIdentity":"Arissana Rocha Nahu: Street Artist","runnerPlayer":2710,"runnerScore":"3","tableNumber":4},{"corpIdentity":"Asa Group: Security Through Vigilance","corpPlayer":2668,"corpScore":"0","runnerIdentity":"Arissana Rocha Nahu: Street Artist","runnerPlayer":2670,"runnerScore":"3","tableNumber":7},{"corpIdentity":"Azmari EdTech: Shaping the Future","corpPlayer":2711,"corpScore":"0","runnerIdentity":"Hoshiko Shiro: Untold Protagonist","runnerPlayer":2706,"runnerScore":"3","tableNumber":2}],[{"corpPlayer":2671,"eliminationGame":true,"loser_id":2669,"runnerPlayer":2669,"tableNumber":2,"winner_id":2671},{"corpPlayer":2706,"eliminationGame":true,"loser_id":2705,"runnerPlayer":2705,"tableNumber":1,"winner_id":2706}],[{"corpPlayer":2669,"eliminationGame":true,"loser_id":2705,"runnerPlayer":2705,"tableNumber":3,"winner_id":2669},{"corpPlayer":2706,"eliminationGame":true,"loser_id":2706,"runnerPlayer":2671,"tableNumber":4,"winner_id":2671}],[{"corpPlayer":2669,"eliminationGame":true,"loser_id":2706,"runnerPlayer":2706,"tableNumber":5,"winner_id":2669}],[{"corpPlayer":2671,"eliminationGame":true,"loser_id":2671,"runnerPlayer":2669,"tableNumber":6,"winner_id":2669}],[{"corpPlayer":2669,"eliminationGame":true,"loser_id":2669,"runnerPlayer":2671,"tableNumber":7,"winner_id":2671}]],"uploadedFrom":"AesopsTables"}